compphysutils/__init__.py
compphysutils/crystalgen/Vector.py
compphysutils/crystalgen/VectorReal.py
compphysutils/crystalgen/VectorRepresentation.py
compphysutils/crystalgen/__init__.py
compphysutils/crystalgen/gencluster
compphysutils/crystalgen/generator.py
compphysutils/crystalgen/readCrystalChar.py
compphysutils/graphics/__init__.py
compphysutils/graphics/atom_plot.py
compphysutils/graphics/decorator.py
compphysutils/graphics/fitter.py
compphysutils/graphics/plot3dcoords
compphysutils/graphics/plotconfig
compphysutils/graphics/plotcoords
compphysutils/graphics/plotter.py
compphysutils/graphics/transformer.py
compphysutils/graphics/decorate/__init__.py
compphysutils/graphics/decorate/arrow.py
compphysutils/graphics/decorate/image.py
compphysutils/graphics/decorate/line.py
compphysutils/graphics/decorate/rect.py
compphysutils/graphics/decorate/text.py
compphysutils/graphics/fit_types/__init__.py
compphysutils/graphics/fit_types/inverse.py
compphysutils/graphics/fit_types/linear.py
compphysutils/graphics/fit_types/lorentz_peak.py
compphysutils/graphics/fit_types/quadratic.py
compphysutils/graphics/plot_types/__init__.py
compphysutils/graphics/plot_types/colormap.py
compphysutils/graphics/plot_types/coord.py
compphysutils/graphics/plot_types/errorbar.py
compphysutils/graphics/plot_types/fill_between.py
compphysutils/graphics/plot_types/level.py
compphysutils/graphics/plot_types/line.py
compphysutils/graphics/plot_types/linlog.py
compphysutils/graphics/plot_types/loglog.py
compphysutils/graphics/plot_types/quiver.py
compphysutils/graphics/plot_types/scatter.py
compphysutils/graphics/transforms/__init__.py
compphysutils/graphics/transforms/log.py
compphysutils/parser/__init__.py
compphysutils/parser/combine.py
compphysutils/parser/parsecoords
compphysutils/parser/parser.py
compphysutils/parser/post_processor.py
compphysutils/parser/runcombine
compphysutils/parser/runparser
compphysutils/parser/savepoint.py
compphysutils/parser/combine_commands/__init__.py
compphysutils-0.4.2.dist-info/licenses/COPYING.reference
compphysutils-0.4.2.dist-info/licenses/LICENSE
compphysutils-0.4.2.dist-info/METADATA
compphysutils-0.4.2.dist-info/WHEEL
compphysutils-0.4.2.dist-info/top_level.txt
compphysutils-0.4.2.dist-info/RECORD
