Metadata-Version: 2.4
Name: compphysutils
Version: 0.4.2
Summary: Set of utilities for computational condensed matter physics
Home-page: https://github.com/StepanMarek/CompPhysUtils
Author: Stepan Marek
Classifier: Programming Language :: Python :: 3
Classifier: License :: OSI Approved :: GNU Lesser General Public License v3 or later (LGPLv3+)
Classifier: Development Status :: 3 - Alpha
Requires-Python: >=3.6
License-File: LICENSE
License-File: COPYING.reference
Requires-Dist: matplotlib>=3.10.1
Requires-Dist: numpy
Requires-Dist: scipy
Requires-Dist: raylib>=5.5.0.0
Dynamic: license-file
